drb_impl_ftp/__init__.py
drb_impl_ftp/_version.py
drb_impl_ftp/basic_auth.py
drb_impl_ftp/cortex.yml
drb_impl_ftp/drb_impl_ftp.py
drb_impl_ftp/execptions.py
drb_impl_ftp-1.0.0.data/data/requirements.txt
drb_impl_ftp-1.0.0.dist-info/METADATA
drb_impl_ftp-1.0.0.dist-info/WHEEL
drb_impl_ftp-1.0.0.dist-info/entry_points.txt
drb_impl_ftp-1.0.0.dist-info/top_level.txt
drb_impl_ftp-1.0.0.dist-info/RECORD
